seisd/AA.py
seisd/__init__.py
seisd/download_stations_info.py
seisd/downloader.py
seisd/gui.py
seisd/realtime_downloader.py
seisd/seisd.py
seisd/seisd_main.py
seisd/test.py
seisd/test_temp.py
seisd/icons/SeisD.png
seisd/icons/SeisY.png
seisd/icons/__init__.py
seisd/icons/波形图.png
seisd/tests/__init__.py
seisd/tests/text_downloader.py
seisd/tests/text_real_time_download.py
SeisD-1.0.0.dist-info/METADATA
SeisD-1.0.0.dist-info/WHEEL
SeisD-1.0.0.dist-info/entry_points.txt
SeisD-1.0.0.dist-info/top_level.txt
SeisD-1.0.0.dist-info/RECORD
